pyqlrtest-0.1.1.dist-info/licenses/License
qlrtest/__init__.py
qlrtest/_exceptions.py
qlrtest/core.py
qlrtest/critical_values.py
qlrtest/utils.py
pyqlrtest-0.1.1.dist-info/METADATA
pyqlrtest-0.1.1.dist-info/WHEEL
pyqlrtest-0.1.1.dist-info/top_level.txt
pyqlrtest-0.1.1.dist-info/RECORD
