Metadata-Version: 2.4
Name: pyqlrtest
Version: 0.1.1
Summary: A Python package for Quandt-Likelihood Ratio (QLR) structural break tests.
Author-email: Jacob Schildknecht <jacob.schildknecht@hotmail.com>
License: MIT License
Project-URL: Homepage, https://github.com/JacobSKN/pyqlrtest
Project-URL: Repository, https://github.com/JacobSKN/pyqlrtest
Keywords: econometrics,time series,structural break,qlr test,supf test,chow test
Classifier: Development Status :: 3 - Alpha
Classifier: Intended Audience :: Science/Research
Classifier: Intended Audience :: Developers
Classifier: License :: OSI Approved :: MIT License
Classifier: Programming Language :: Python :: 3
Classifier: Programming Language :: Python :: 3.8
Classifier: Programming Language :: Python :: 3.9
Classifier: Programming Language :: Python :: 3.10
Classifier: Programming Language :: Python :: 3.11
Classifier: Programming Language :: Python :: 3.12
Classifier: Operating System :: OS Independent
Classifier: Topic :: Scientific/Engineering :: Mathematics
Classifier: Topic :: Software Development :: Libraries :: Python Modules
Requires-Python: >=3.8
License-File: License
Requires-Dist: numpy>=1.20
Requires-Dist: scipy>=1.7
Requires-Dist: statsmodels>=0.13
Requires-Dist: pandas>=1.3
Dynamic: license-file
